konfsave/__init__.py
konfsave/__main__.py
konfsave/actions.py
konfsave/config.py
konfsave/constants.py
konfsave/default_config.ini
konfsave/profiles/__init__.py
konfsave/profiles/archive.py
konfsave/profiles/load.py
konfsave/profiles/manage.py
konfsave/profiles/save.py
konfsave/profiles/utils.py
konfsave-0.4.2.dist-info/LICENSE
konfsave-0.4.2.dist-info/METADATA
konfsave-0.4.2.dist-info/WHEEL
konfsave-0.4.2.dist-info/entry_points.txt
konfsave-0.4.2.dist-info/top_level.txt
konfsave-0.4.2.dist-info/RECORD
