Metadata-Version: 2.1
Name: konfsave
Version: 0.4.2
Summary: Easy saving and switching between multiple KDE configurations.
Home-page: https://github.com/selplacei/konfsave
Author: selplacei
Author-email: ilyaviaik@gmail.com
License: Apache 2.0
Project-URL: Issue Tracker, https://github.com/selplacei/konfsave/issues
Platform: UNKNOWN
Classifier: Programming Language :: Python :: 3
Classifier: License :: OSI Approved :: Apache Software License
Classifier: Development Status :: 3 - Alpha
Classifier: Intended Audience :: End Users/Desktop
Classifier: Topic :: Desktop Environment :: K Desktop Environment (KDE)
Classifier: Topic :: System :: Archiving
Requires-Python: >=3.8
Provides-Extra: git
Requires-Dist: pygit2 ; extra == 'git'
